{
  "_readme": "한국 시장 이슈(KRX 수급 데이터 해석) 원본. 마켓 브리프 세션이 이 파일만 갱신하면 build_briefing.py가 '한국 시장 이슈' 섹션에 주입한다. HTML을 직접 편집하지 말 것. 스키마는 data/us_issues.json과 동일 — title/desc[]/impacts[{strategy,level,text}]. level: g(우호)·w(중립)·c(경고)·s(심각). 날짜 라벨은 별도 필드 없이 KRX 스냅샷의 기준일(asof)을 그대로 재사용한다.",
  "issues": [
    {
      "title": "7/20 코스피 −4.46% 재차 급락(6,516.27, 조정 국면 신저가) — 보험·기계장비·유통 등 전방위 매도 속 외국인은 되레 순매수 전환(+5,272억), 하이닉스 홀로 +6,111억",
      "desc": [
        "7/20(월) 코스피는 −4.46%(6,516.27)로 재차 급락, 3거래일 전 저점(7/16 6,820.60)마저 하회하며 이 조정 국면의 신저가를 경신했다(장중 저가 6,472.80, 고가 6,814.86 — 시가 6,820.60에서 갭다운 출발 후 낙폭 확대, KRX 공식 확정). 이번 낙폭은 7/16과 달리 반도체가 아니라 보험(−8.98%)·기계장비(−7.22%, 방산·전력기기 포함)·유통(−6.27%)·의료정밀기기(−5.86%)·증권(−5.79%) 등 전방위 업종에서 나왔다 — 전기전자(−4.43%)·제조(−4.51%)는 오히려 지수 평균에 못 미치는 낙폭이었다.",
        "수급은 이례적인 엇박자를 보였다: 코스피 전체로는 외국인이 +5,272억 순매수로 전환(7/16 −1조 3,814억에서 반전)했음에도 지수는 급락했다 — 매도 주체는 기관(−9,235억, 금융투자 −4,931억·투신 −2,675억·사모 −2,901억 주도, 연기금은 +742억 소폭 매수)이었고 개인은 +3,490억 순매수. 외국인 순매수 1위는 SK하이닉스 +6,111억(외국인 전체 순매수의 대부분을 차지), 2위 삼성전자 +2,852억, 3위 삼성전자우 +1,221억로 반도체 투톱에 집중됐다 — 순매도 1위는 한화오션(−507억)·삼성전기(−502억)·현대차(−353억).",
        "이 엇박자(외국인 반도체 집중 순매수 vs 지수 전방위 급락)는 Add 트리거의 두 조건 중 수급 조건(외국인 순매수 전환)은 하루치 충족했으나 가격 조건은 오히려 후퇴했음을 뜻한다 — 종가 6,516.27은 매수구간(7,000~7,200) 하단과 6.9% 격차로, 이 조정 국면 중 가장 크게 벌어졌다(7/16 장중 고가는 구간과 0.1%도 안 되는 거리였다). 손익비 참고용 손절선은 6,500 → 6,000으로 재설정했다 — 6,500은 시나리오 매트릭스 베어 케이스(KOSPI 6,000~6,500) 상단이었는데 7/20 장중 저가(6,472.80)가 이미 그 범위 안으로 들어와 더 이상 유효한 참고점이 아니었기 때문이다. 새 참고선(베어 케이스 하단 6,000) 기준 손익비는 상방 +53.5%(불케이스 10,000) / 하방 −7.9%.",
        "코스닥도 −5.33%(749.64)로 동반 급락 — 외국인 −560억·기관 −1,330억 순매도, 개인 +1,907억 순매수로 코스피와 유사한 구조지만 낙폭은 코스피보다 컸다."
      ],
      "impacts": [
        {"strategy": "A 바벨", "level": "c", "text": "Add 트리거 수급 조건(외국인 순매수 전환)은 하루치 충족됐으나 가격 조건은 후퇴 — 구간과의 거리가 6.9%로 이 조정 국면 중 최대. 손익비 참고 손절선을 6,500(장중 하회)에서 시나리오 매트릭스 베어 케이스 하단 6,000으로 재설정(상방 +53.5%/하방 −7.9%). approaching 유지하되 추격·선행 매수는 계속 금지, 구간 재진입 종가+수급 지속 동시 확인까지 대기."},
        {"strategy": "B 모멘텀", "level": "w", "text": "SK하이닉스 외국인 순매수 +6,111억(외국인 전체 순매수의 대부분)은 Flow Watch에 우호적 반전 신호이나, 단 하루치라 '2~3일 지속 확인' 원칙상 dormant 전환은 아직 이르다 — approaching 유지, 내일 지속 여부가 핵심 관찰 포인트."}
      ]
    },
    {
      "title": "이달 누적 수급(7/1~7/20) — 외국인 순매도 11.6조로 소폭 축소, 개인 누적 순매수 10.7조로 확대",
      "desc": [
        "7월 들어(7/1~7/20) 외국인은 코스피에서 11.64조 순매도로, 직전 확인(7/1~7/16 −12.16조) 대비 소폭 축소됐다 — 7/20 하루치 순매수(+5,272억)가 반영된 결과. 개인은 이달 +10.65조 순매수로 확대, 기관합계는 +4,179억으로 축소(7/20 −9,235억 순매도 반영).",
        "연초 누적(1/2~7/20)은 외국인 −160.7조 vs 개인 +109.8조·기관 +35.5조 — 외국인 이탈 총량은 여전히 막대하지만 이달 들어서는 소폭 개선되는 모습.",
        "코스닥은 이달 외국인 −4,019억 순매도로 확대, 개인은 +1,519억 순매수로 전환(7/20 하루 +1,907억 매수가 이달 누적을 순매수 쪽으로 되돌렸다)."
      ],
      "impacts": [
        {"strategy": "A 바벨", "level": "w", "text": "외국인 이달 누적 이탈이 소폭 축소됐지만 하루치 반전만으로 추세 전환을 단정하기는 이르다 — 지속성 확인이 핵심."},
        {"strategy": "B 모멘텀", "level": "w", "text": "반도체 대형주 수급이 일 단위로 크게 뒤집히는 구간이 계속되고 있다 — 종목 선별 기조 유지, 수급 시그널은 최소 2~3일 지속 확인 후 반영."}
      ]
    }
  ]
}
